{
    "type": "Screen",
    "translatedName": "Screen",
    "reactType": "ViewWithProps",
    "properties": {
        "Height": "Fill container",
        "Width": "Fill container",
        "Layout": "column",
        "Justification": "center",
        "Alignment": "center",
        "Visible": true,
        "style": {
            "marginTop": 0,
            "marginBottom": 0,
            "marginLeft": 0,
            "marginRight": 0,
            "paddingTop": 0,
            "paddingBottom": 0,
            "paddingLeft": 0,
            "paddingRight": 0,
            "shadowColor": "rgba(0, 0, 0, 0)",
            "shadowOpacity": 0,
            "scaledShadowOpacity": 0,
            "shadowRadius": 0,
            "shadowOffset": {
                "width": 0,
                "height": 0
            },
            "flexDirection": "column",
            "justifyContent": "center",
            "alignItems": "center",
            "display": "flex"
        },
        "ShowStatusBar": true,
        "StatusBarStyle": "default",
        "TranslucentStatusBar": false,
        "StatusBarColor": "rgba(0,0,0,0.53)",
        "TabNavigationOptions": {
            "tabBarVisible": true
        },
        "TabNavigatorIcon": {},
        "DrawerNavigationOptions": {},
        "StackNavigationOptions": {
            "headerStyle": {}
        },
        "ScreenOrientation": "portrait",
        "DesignerHeight": 667,
        "DesignerWidth": 375,
        "ResponsiveWidth": 375,
        "isSimple": true,
        "navigationOptions": {
            "headerStyle": {}
        },
        "tabNavigationOptions": {}
    },
    "children": [
        {
            "type": "Button",
            "translatedName": "Button",
            "properties": {
                "Text": "Reset",
                "TextColor": "rgba(74, 144, 226, 0.78)",
                "FontSize": 16,
                "CustomFont": "",
                "BackgroundColor": "rgba(0, 0, 0, 0)",
                "Height": 41,
                "Width": 125,
                "Visible": true,
                "X": 117,
                "Y": 418,
                "RelativeX": 117,
                "RelativeY": 418,
                "ResizeMode": "STRETCH",
                "style": {
                    "marginTop": 0,
                    "marginBottom": 0,
                    "marginLeft": 0,
                    "marginRight": 0,
                    "paddingTop": 0,
                    "paddingBottom": 0,
                    "paddingLeft": 0,
                    "paddingRight": 0,
                    "borderRadius": 15,
                    "shadowColor": "rgba(0, 0, 0, 0)",
                    "shadowOpacity": 0,
                    "scaledShadowOpacity": 0,
                    "shadowRadius": 0,
                    "shadowOffset": {
                        "width": 0,
                        "height": 0
                    },
                    "position": "absolute",
                    "left": "50%",
                    "top": "75.74213076567185%",
                    "display": "flex"
                },
                "FontBold": false,
                "FontItalic": false,
                "Raised": false,
                "Disabled": false,
                "ParentId": "0ede0772-f09d-4647-bc51-655ec20af25e",
                "position": "absolute",
                "edgeOffsets": 418
            },
            "children": [],
            "id": "0aca8797-70cc-4452-8992-d92838795391",
            "thunkableVersion": 422,
            "name": "resetBtn"
        },
        {
            "type": "Button",
            "translatedName": "Button",
            "properties": {
                "Text": "Sign out",
                "TextColor": "#FFFFFF",
                "FontSize": 16,
                "CustomFont": "",
                "BackgroundColor": "rgba(93, 122, 252, 100)",
                "Height": 55,
                "Width": 112,
                "Visible": true,
                "X": 130,
                "Y": 332,
                "RelativeX": 130,
                "RelativeY": 332,
                "ResizeMode": "STRETCH",
                "style": {
                    "marginTop": 0,
                    "marginBottom": 0,
                    "marginLeft": 0,
                    "marginRight": 0,
                    "paddingTop": 0,
                    "paddingBottom": 0,
                    "paddingLeft": 0,
                    "paddingRight": 0,
                    "borderRadius": 15,
                    "shadowColor": "rgba(0, 0, 0, 0)",
                    "shadowOpacity": 0,
                    "scaledShadowOpacity": 0,
                    "shadowRadius": 0,
                    "shadowOffset": {
                        "width": 0,
                        "height": 0
                    },
                    "position": "absolute",
                    "left": "37.733333333333334%",
                    "top": "64.88505625117129%",
                    "display": "flex"
                },
                "FontBold": false,
                "FontItalic": false,
                "Raised": false,
                "Disabled": false,
                "ParentId": "0ede0772-f09d-4647-bc51-655ec20af25e",
                "position": "absolute",
                "edgeOffsets": 332
            },
            "children": [],
            "id": "6490f980-c2b5-4913-bf4f-df15f606f51f",
            "thunkableVersion": 422,
            "name": "signoutBtn"
        },
        {
            "type": "Label",
            "translatedName": "Label",
            "reactType": "Text",
            "properties": {
                "Text": "Signed in!",
                "FontSize": 18,
                "CustomFont": "",
                "LineHeight": 1,
                "Color": "rgba(0, 0, 0, 1)",
                "TextAlign": "center",
                "Height": 45,
                "Width": 311,
                "Visible": true,
                "X": 32,
                "Y": 159,
                "RelativeX": 32,
                "RelativeY": 159,
                "ResizeMode": "STRETCH",
                "style": {
                    "color": "rgba(0, 0, 0, 1)",
                    "fontSize": 18,
                    "fontStyle": "normal",
                    "textShadowOffset": {},
                    "letterSpacing": 0,
                    "textDecorationLine": "none",
                    "textDecorationStyle": "solid",
                    "textDecorationColor": "rgba(0, 0, 0, 1)",
                    "writingDirection": "auto",
                    "marginTop": 0,
                    "marginBottom": 0,
                    "marginLeft": 0,
                    "marginRight": 0,
                    "paddingTop": 0,
                    "paddingBottom": 0,
                    "paddingLeft": 0,
                    "paddingRight": 0,
                    "flexWrap": "wrap",
                    "borderWidth": 0,
                    "borderRadius": 0,
                    "borderColor": "rgba(236, 237, 237, 1)",
                    "borderStyle": "solid",
                    "shadowColor": "rgba(0, 0, 0, 0)",
                    "shadowOpacity": 0,
                    "scaledShadowOpacity": 0,
                    "shadowRadius": 0,
                    "shadowOffset": {
                        "width": 0,
                        "height": 0
                    },
                    "position": "absolute",
                    "left": "31.6%",
                    "top": "20.057470044274737%",
                    "lineHeight": 1,
                    "display": "flex",
                    "textAlign": "center"
                },
                "ParentId": "0ede0772-f09d-4647-bc51-655ec20af25e",
                "position": "absolute",
                "edgeOffsets": 159,
                "children": "Signed in!"
            },
            "children": [],
            "id": "6f13c2eb-5c88-44da-9963-202b4fe6d4b8",
            "thunkableVersion": 422,
            "name": "signedinLbl"
        },
        {
            "type": "Image",
            "translatedName": "Image",
            "properties": {
                "Picture": "305soft.png",
                "resizeMode": "stretch",
                "Height": 78,
                "Width": 87,
                "Visible": true,
                "X": 136,
                "Y": 0,
                "RelativeX": 136,
                "RelativeY": 0,
                "ResizeMode": "STRETCH",
                "style": {
                    "marginTop": 0,
                    "marginBottom": 0,
                    "marginLeft": 0,
                    "marginRight": 0,
                    "paddingTop": 0,
                    "paddingBottom": 0,
                    "paddingLeft": 0,
                    "paddingRight": 0,
                    "shadowColor": "rgba(0, 0, 0, 0)",
                    "shadowOpacity": 0,
                    "scaledShadowOpacity": 0,
                    "shadowRadius": 0,
                    "shadowOffset": {
                        "width": 0,
                        "height": 0
                    },
                    "position": "absolute",
                    "left": "39.6%",
                    "top": "0%",
                    "display": "flex"
                },
                "capInsets": {},
                "ParentId": "0ede0772-f09d-4647-bc51-655ec20af25e",
                "position": "absolute",
                "edgeOffsets": 0
            },
            "children": [],
            "id": "9580c32b-7171-476f-a221-f950be97bccb",
            "thunkableVersion": 422,
            "name": "305softlogo1"
        }
    ],
    "id": "0ede0772-f09d-4647-bc51-655ec20af25e",
    "thunkableVersion": 422,
    "name": "Screen2"
}